{
  "name": "kbd-variants-demo",
  "type": "registry:example",
  "files": [
    {
      "path": "example/kbd-variants-demo.tsx",
      "content": "import * as Kbd from \"@/registry/default/ui/kbd\";\r\n\r\nexport default function KbdVariantsDemo() {\r\n  return (\r\n    <div className=\"flex flex-col gap-8\">\r\n      <div className=\"flex flex-col gap-2\">\r\n        <p className=\"text-muted-foreground text-sm\">Default</p>\r\n        <Kbd.Root>\r\n          <Kbd.Key>⌘</Kbd.Key>\r\n          <Kbd.Separator />\r\n          <Kbd.Key>K</Kbd.Key>\r\n        </Kbd.Root>\r\n      </div>\r\n      <div className=\"flex flex-col gap-2\">\r\n        <p className=\"text-muted-foreground text-sm\">Outline</p>\r\n        <Kbd.Root variant=\"outline\">\r\n          <Kbd.Key>⎋</Kbd.Key>\r\n          <Kbd.Separator />\r\n          <Kbd.Key description=\"Escape\">Esc</Kbd.Key>\r\n        </Kbd.Root>\r\n      </div>\r\n      <div className=\"flex flex-col gap-2\">\r\n        <p className=\"text-muted-foreground text-sm\">Ghost</p>\r\n        <Kbd.Root variant=\"ghost\">\r\n          <Kbd.Key>⌤</Kbd.Key>\r\n          <Kbd.Separator />\r\n          <Kbd.Key description=\"Return\">Enter</Kbd.Key>\r\n        </Kbd.Root>\r\n      </div>\r\n      <div className=\"flex flex-col gap-2\">\r\n        <p className=\"text-muted-foreground text-sm\">Function keys</p>\r\n        <div className=\"flex gap-2\">\r\n          <Kbd.Root variant=\"outline\">\r\n            <Kbd.Key description=\"Function key 1\">F1</Kbd.Key>\r\n          </Kbd.Root>\r\n          <Kbd.Root variant=\"outline\">\r\n            <Kbd.Key description=\"Function key 5\">F5</Kbd.Key>\r\n          </Kbd.Root>\r\n          <Kbd.Root variant=\"outline\">\r\n            <Kbd.Key description=\"Function key 11\">F11</Kbd.Key>\r\n          </Kbd.Root>\r\n        </div>\r\n      </div>\r\n      <div className=\"flex flex-col gap-2\">\r\n        <p className=\"text-muted-foreground text-sm\">Mixed variants</p>\r\n        <div className=\"flex gap-2\">\r\n          <Kbd.Root>\r\n            <Kbd.Key>⌘</Kbd.Key>\r\n            <Kbd.Separator />\r\n            <Kbd.Key>⇧</Kbd.Key>\r\n            <Kbd.Separator />\r\n            <Kbd.Key description=\"Find in files\">F</Kbd.Key>\r\n          </Kbd.Root>\r\n          <Kbd.Root variant=\"outline\">\r\n            <Kbd.Key>⌥</Kbd.Key>\r\n            <Kbd.Separator />\r\n            <Kbd.Key description=\"Quick fix\">.</Kbd.Key>\r\n          </Kbd.Root>\r\n        </div>\r\n      </div>\r\n    </div>\r\n  );\r\n}\r\n",
      "type": "registry:example",
      "target": ""
    }
  ]
}